{"metadata": {"datasets": ["NDF", "TSDF"]}, "data": [{"startTime": "2024-09-09T00:00:00Z", "settlementDate": "2024-09-09", "settlementPeriod": 3, "boundary": "N", "publishTime": "2024-09-08T23:45:00Z", "transmissionSystemDemand": 19547, "nationalDemand": 18100}, {"startTime": "2024-09-09T00:30:00Z", "settlementDate": "2024-09-09", "settlementPeriod": 4, "boundary": "N", "publishTime": "2024-09-09T00:15:00Z", "transmissionSystemDemand": 19667, "nationalDemand": 18200}, {"startTime": "2024-09-09T01:00:00Z", "settlementDate": "2024-09-09", "settlementPeriod": 5, "boundary": "N", "publishTime": "2024-09-09T00:45:00Z", "transmissionSystemDemand": 19996, "nationalDemand": 17925}, {"startTime": "2024-09-09T01:30:00Z", "settlementDate": "2024-09-09", "settlementPeriod": 6, "boundary": "N", "publishTime": "2024-09-09T01:15:00Z", "transmissionSystemDemand": 19585, "nationalDemand": 17490}, {"startTime": "2024-09-09T02:00:00Z", "settlementDate": "2024-09-09", "settlementPeriod": 7, "boundary": "N", "publishTime": "2024-09-09T01:45:00Z", "transmissionSystemDemand": 20064, "nationalDemand": 17409}, {"startTime": "2024-09-09T02:30:00Z", "settlementDate": "2024-09-09", "settlementPeriod": 8, "boundary": "N", "publishTime": "2024-09-09T02:15:00Z", "transmissionSystemDemand": 19924, "nationalDemand": 17215}, {"startTime": "2024-09-09T03:00:00Z", "settlementDate": "2024-09-09", "settlementPeriod": 9, "boundary": "N", "publishTime": "2024-09-09T02:45:00Z", "transmissionSystemDemand": 19813, "nationalDemand": 17000}, {"startTime": "2024-09-09T03:30:00Z", "settlementDate": "2024-09-09", "settlementPeriod": 10, "boundary": "N", "publishTime": "2024-09-09T03:15:00Z", "transmissionSystemDemand": 20025, "nationalDemand": 17064}, {"startTime": "2024-09-09T04:00:00Z", "settlementDate": "2024-09-09", "settlementPeriod": 11, "boundary": "N", "publishTime": "2024-09-09T03:45:00Z", "transmissionSystemDemand": 20585, "nationalDemand": 17474}, {"startTime": "2024-09-09T04:30:00Z", "settlementDate": "2024-09-09", "settlementPeriod": 12, "boundary": "N", "publishTime": "2024-09-09T04:15:00Z", "transmissionSystemDemand": 21514, "nationalDemand": 18527}, {"startTime": "2024-09-09T05:00:00Z", "settlementDate": "2024-09-09", "settlementPeriod": 13, "boundary": "N", "publishTime": "2024-09-09T04:45:00Z", "transmissionSystemDemand": 23918, "nationalDemand": 20515}, {"startTime": "2024-09-09T05:30:00Z", "settlementDate": "2024-09-09", "settlementPeriod": 14, "boundary": "N", "publishTime": "2024-09-09T05:15:00Z", "transmissionSystemDemand": 26045, "nationalDemand": 22462}, {"startTime": "2024-09-09T06:00:00Z", "settlementDate": "2024-09-09", "settlementPeriod": 15, "boundary": "N", "publishTime": "2024-09-09T05:45:00Z", "transmissionSystemDemand": 28259, "nationalDemand": 24687}, {"startTime": "2024-09-09T06:30:00Z", "settlementDate": "2024-09-09", "settlementPeriod": 16, "boundary": "N", "publishTime": "2024-09-09T06:15:00Z", "transmissionSystemDemand": 29270, "nationalDemand": 25600}, {"startTime": "2024-09-09T07:00:00Z", "settlementDate": "2024-09-09", "settlementPeriod": 17, "boundary": "N", "publishTime": "2024-09-09T06:45:00Z", "transmissionSystemDemand": 30540, "nationalDemand": 27103}, {"startTime": "2024-09-09T07:30:00Z", "settlementDate": "2024-09-09", "settlementPeriod": 18, "boundary": "N", "publishTime": "2024-09-09T07:15:00Z", "transmissionSystemDemand": 30871, "nationalDemand": 27421}, {"startTime": "2024-09-09T08:00:00Z", "settlementDate": "2024-09-09", "settlementPeriod": 19, "boundary": "N", "publishTime": "2024-09-09T07:15:00Z", "transmissionSystemDemand": 30808, "nationalDemand": 27700}, {"startTime": "2024-09-09T08:30:00Z", "settlementDate": "2024-09-09", "settlementPeriod": 20, "boundary": "N", "publishTime": "2024-09-09T08:15:00Z", "transmissionSystemDemand": 30373, "nationalDemand": 27277}, {"startTime": "2024-09-09T09:00:00Z", "settlementDate": "2024-09-09", "settlementPeriod": 21, "boundary": "N", "publishTime": "2024-09-09T08:45:00Z", "transmissionSystemDemand": 29751, "nationalDemand": 26801}, {"startTime": "2024-09-09T09:30:00Z", "settlementDate": "2024-09-09", "settlementPeriod": 22, "boundary": "N", "publishTime": "2024-09-09T09:15:00Z", "transmissionSystemDemand": 29400, "nationalDemand": 26600}, {"startTime": "2024-09-09T10:00:00Z", "settlementDate": "2024-09-09", "settlementPeriod": 23, "boundary": "N", "publishTime": "2024-09-09T09:45:00Z", "transmissionSystemDemand": 28217, "nationalDemand": 26497}, {"startTime": "2024-09-09T10:30:00Z", "settlementDate": "2024-09-09", "settlementPeriod": 24, "boundary": "N", "publishTime": "2024-09-09T10:15:00Z", "transmissionSystemDemand": 28124, "nationalDemand": 26543}, {"startTime": "2024-09-09T11:00:00Z", "settlementDate": "2024-09-09", "settlementPeriod": 25, "boundary": "N", "publishTime": "2024-09-09T10:45:00Z", "transmissionSystemDemand": 27702, "nationalDemand": 26700}, {"startTime": "2024-09-09T11:30:00Z", "settlementDate": "2024-09-09", "settlementPeriod": 26, "boundary": "N", "publishTime": "2024-09-09T11:15:00Z", "transmissionSystemDemand": 27255, "nationalDemand": 26435}, {"startTime": "2024-09-09T12:00:00Z", "settlementDate": "2024-09-09", "settlementPeriod": 27, "boundary": "N", "publishTime": "2024-09-09T11:45:00Z", "transmissionSystemDemand": 27114, "nationalDemand": 26200}, {"startTime": "2024-09-09T12:30:00Z", "settlementDate": "2024-09-09", "settlementPeriod": 28, "boundary": "N", "publishTime": "2024-09-09T12:15:00Z", "transmissionSystemDemand": 26444, "nationalDemand": 25518}, {"startTime": "2024-09-09T13:00:00Z", "settlementDate": "2024-09-09", "settlementPeriod": 29, "boundary": "N", "publishTime": "2024-09-09T12:45:00Z", "transmissionSystemDemand": 26956, "nationalDemand": 24890}, {"startTime": "2024-09-09T13:30:00Z", "settlementDate": "2024-09-09", "settlementPeriod": 30, "boundary": "N", "publishTime": "2024-09-09T13:15:00Z", "transmissionSystemDemand": 26516, "nationalDemand": 24421}, {"startTime": "2024-09-09T14:00:00Z", "settlementDate": "2024-09-09", "settlementPeriod": 31, "boundary": "N", "publishTime": "2024-09-09T13:45:00Z", "transmissionSystemDemand": 25580, "nationalDemand": 24000}, {"startTime": "2024-09-09T14:30:00Z", "settlementDate": "2024-09-09", "settlementPeriod": 32, "boundary": "N", "publishTime": "2024-09-09T14:15:00Z", "transmissionSystemDemand": 25937, "nationalDemand": 24287}, {"startTime": "2024-09-09T15:00:00Z", "settlementDate": "2024-09-09", "settlementPeriod": 33, "boundary": "N", "publishTime": "2024-09-09T14:45:00Z", "transmissionSystemDemand": 26462, "nationalDemand": 24972}, {"startTime": "2024-09-09T15:30:00Z", "settlementDate": "2024-09-09", "settlementPeriod": 34, "boundary": "N", "publishTime": "2024-09-09T15:15:00Z", "transmissionSystemDemand": 27351, "nationalDemand": 25933}, {"startTime": "2024-09-09T16:00:00Z", "settlementDate": "2024-09-09", "settlementPeriod": 35, "boundary": "N", "publishTime": "2024-09-09T15:45:00Z", "transmissionSystemDemand": 28177, "nationalDemand": 27399}, {"startTime": "2024-09-09T16:30:00Z", "settlementDate": "2024-09-09", "settlementPeriod": 36, "boundary": "N", "publishTime": "2024-09-09T16:15:00Z", "transmissionSystemDemand": 28929, "nationalDemand": 28184}, {"startTime": "2024-09-09T17:00:00Z", "settlementDate": "2024-09-09", "settlementPeriod": 37, "boundary": "N", "publishTime": "2024-09-09T16:45:00Z", "transmissionSystemDemand": 29365, "nationalDemand": 28865}, {"startTime": "2024-09-09T17:30:00Z", "settlementDate": "2024-09-09", "settlementPeriod": 38, "boundary": "N", "publishTime": "2024-09-09T17:15:00Z", "transmissionSystemDemand": 29830, "nationalDemand": 29330}, {"startTime": "2024-09-09T18:00:00Z", "settlementDate": "2024-09-09", "settlementPeriod": 39, "boundary": "N", "publishTime": "2024-09-09T17:45:00Z", "transmissionSystemDemand": 30711, "nationalDemand": 29992}, {"startTime": "2024-09-09T18:30:00Z", "settlementDate": "2024-09-09", "settlementPeriod": 40, "boundary": "N", "publishTime": "2024-09-09T18:15:00Z", "transmissionSystemDemand": 30763, "nationalDemand": 30020}, {"startTime": "2024-09-09T19:00:00Z", "settlementDate": "2024-09-09", "settlementPeriod": 41, "boundary": "N", "publishTime": "2024-09-09T18:45:00Z", "transmissionSystemDemand": 30103, "nationalDemand": 29154}, {"startTime": "2024-09-09T19:30:00Z", "settlementDate": "2024-09-09", "settlementPeriod": 42, "boundary": "N", "publishTime": "2024-09-09T19:15:00Z", "transmissionSystemDemand": 29046, "nationalDemand": 27906}, {"startTime": "2024-09-09T20:00:00Z", "settlementDate": "2024-09-09", "settlementPeriod": 43, "boundary": "N", "publishTime": "2024-09-09T19:45:00Z", "transmissionSystemDemand": 28156, "nationalDemand": 26747}, {"startTime": "2024-09-09T20:30:00Z", "settlementDate": "2024-09-09", "settlementPeriod": 44, "boundary": "N", "publishTime": "2024-09-09T20:15:00Z", "transmissionSystemDemand": 27028, "nationalDemand": 25598}, {"startTime": "2024-09-09T21:00:00Z", "settlementDate": "2024-09-09", "settlementPeriod": 45, "boundary": "N", "publishTime": "2024-09-09T20:45:00Z", "transmissionSystemDemand": 25945, "nationalDemand": 24033}, {"startTime": "2024-09-09T21:30:00Z", "settlementDate": "2024-09-09", "settlementPeriod": 46, "boundary": "N", "publishTime": "2024-09-09T21:15:00Z", "transmissionSystemDemand": 24481, "nationalDemand": 22689}, {"startTime": "2024-09-09T22:00:00Z", "settlementDate": "2024-09-09", "settlementPeriod": 47, "boundary": "N", "publishTime": "2024-09-09T21:45:00Z", "transmissionSystemDemand": 23285, "nationalDemand": 21016}, {"startTime": "2024-09-09T22:30:00Z", "settlementDate": "2024-09-09", "settlementPeriod": 48, "boundary": "N", "publishTime": "2024-09-09T22:15:00Z", "transmissionSystemDemand": 22062, "nationalDemand": 19900}, {"startTime": "2024-09-09T23:00:00Z", "settlementDate": "2024-09-10", "settlementPeriod": 1, "boundary": "N", "publishTime": "2024-09-09T22:45:00Z", "transmissionSystemDemand": 22690, "nationalDemand": 19200}, {"startTime": "2024-09-09T23:30:00Z", "settlementDate": "2024-09-10", "settlementPeriod": 2, "boundary": "N", "publishTime": "2024-09-09T23:15:00Z", "transmissionSystemDemand": 22189, "nationalDemand": 18679}, {"startTime": "2024-09-10T00:00:00Z", "settlementDate": "2024-09-10", "settlementPeriod": 3, "boundary": "N", "publishTime": "2024-09-09T23:45:00Z", "transmissionSystemDemand": 22593, "nationalDemand": 18210}, {"startTime": "2024-09-10T00:30:00Z", "settlementDate": "2024-09-10", "settlementPeriod": 4, "boundary": "N", "publishTime": "2024-09-10T00:15:00Z", "transmissionSystemDemand": 22287, "nationalDemand": 17940}, {"startTime": "2024-09-10T01:00:00Z", "settlementDate": "2024-09-10", "settlementPeriod": 5, "boundary": "N", "publishTime": "2024-09-10T00:45:00Z", "transmissionSystemDemand": 21956, "nationalDemand": 17391}, {"startTime": "2024-09-10T01:30:00Z", "settlementDate": "2024-09-10", "settlementPeriod": 6, "boundary": "N", "publishTime": "2024-09-10T01:15:00Z", "transmissionSystemDemand": 21663, "nationalDemand": 16922}, {"startTime": "2024-09-10T02:00:00Z", "settlementDate": "2024-09-10", "settlementPeriod": 7, "boundary": "N", "publishTime": "2024-09-10T01:45:00Z", "transmissionSystemDemand": 21328, "nationalDemand": 16643}, {"startTime": "2024-09-10T02:30:00Z", "settlementDate": "2024-09-10", "settlementPeriod": 8, "boundary": "N", "publishTime": "2024-09-10T02:15:00Z", "transmissionSystemDemand": 20978, "nationalDemand": 16223}, {"startTime": "2024-09-10T03:00:00Z", "settlementDate": "2024-09-10", "settlementPeriod": 9, "boundary": "N", "publishTime": "2024-09-10T02:45:00Z", "transmissionSystemDemand": 21756, "nationalDemand": 16160}, {"startTime": "2024-09-10T03:30:00Z", "settlementDate": "2024-09-10", "settlementPeriod": 10, "boundary": "N", "publishTime": "2024-09-10T03:15:00Z", "transmissionSystemDemand": 21937, "nationalDemand": 16304}, {"startTime": "2024-09-10T04:00:00Z", "settlementDate": "2024-09-10", "settlementPeriod": 11, "boundary": "N", "publishTime": "2024-09-10T03:45:00Z", "transmissionSystemDemand": 22349, "nationalDemand": 16817}, {"startTime": "2024-09-10T04:30:00Z", "settlementDate": "2024-09-10", "settlementPeriod": 12, "boundary": "N", "publishTime": "2024-09-10T04:15:00Z", "transmissionSystemDemand": 23166, "nationalDemand": 17766}, {"startTime": "2024-09-10T05:00:00Z", "settlementDate": "2024-09-10", "settlementPeriod": 13, "boundary": "N", "publishTime": "2024-09-10T04:45:00Z", "transmissionSystemDemand": 23351, "nationalDemand": 19311}, {"startTime": "2024-09-10T05:30:00Z", "settlementDate": "2024-09-10", "settlementPeriod": 14, "boundary": "N", "publishTime": "2024-09-10T05:15:00Z", "transmissionSystemDemand": 24663, "nationalDemand": 21121}, {"startTime": "2024-09-10T06:00:00Z", "settlementDate": "2024-09-10", "settlementPeriod": 15, "boundary": "N", "publishTime": "2024-09-10T05:45:00Z", "transmissionSystemDemand": 26834, "nationalDemand": 23091}, {"startTime": "2024-09-10T06:30:00Z", "settlementDate": "2024-09-10", "settlementPeriod": 16, "boundary": "N", "publishTime": "2024-09-10T06:15:00Z", "transmissionSystemDemand": 28096, "nationalDemand": 24200}, {"startTime": "2024-09-10T07:00:00Z", "settlementDate": "2024-09-10", "settlementPeriod": 17, "boundary": "N", "publishTime": "2024-09-10T06:45:00Z", "transmissionSystemDemand": 27768, "nationalDemand": 25346}, {"startTime": "2024-09-10T07:30:00Z", "settlementDate": "2024-09-10", "settlementPeriod": 18, "boundary": "N", "publishTime": "2024-09-10T07:15:00Z", "transmissionSystemDemand": 27748, "nationalDemand": 25326}, {"startTime": "2024-09-10T08:00:00Z", "settlementDate": "2024-09-10", "settlementPeriod": 19, "boundary": "N", "publishTime": "2024-09-10T07:15:00Z", "transmissionSystemDemand": 28023, "nationalDemand": 26000}, {"startTime": "2024-09-10T08:30:00Z", "settlementDate": "2024-09-10", "settlementPeriod": 20, "boundary": "N", "publishTime": "2024-09-10T08:15:00Z", "transmissionSystemDemand": 28071, "nationalDemand": 25994}, {"startTime": "2024-09-10T09:00:00Z", "settlementDate": "2024-09-10", "settlementPeriod": 21, "boundary": "N", "publishTime": "2024-09-10T08:45:00Z", "transmissionSystemDemand": 27773, "nationalDemand": 25510}, {"startTime": "2024-09-10T09:30:00Z", "settlementDate": "2024-09-10", "settlementPeriod": 22, "boundary": "N", "publishTime": "2024-09-10T09:15:00Z", "transmissionSystemDemand": 27809, "nationalDemand": 25346}, {"startTime": "2024-09-10T10:00:00Z", "settlementDate": "2024-09-10", "settlementPeriod": 23, "boundary": "N", "publishTime": "2024-09-10T09:45:00Z", "transmissionSystemDemand": 27474, "nationalDemand": 25079}, {"startTime": "2024-09-10T10:30:00Z", "settlementDate": "2024-09-10", "settlementPeriod": 24, "boundary": "N", "publishTime": "2024-09-10T10:15:00Z", "transmissionSystemDemand": 27159, "nationalDemand": 24771}, {"startTime": "2024-09-10T11:00:00Z", "settlementDate": "2024-09-10", "settlementPeriod": 25, "boundary": "N", "publishTime": "2024-09-10T10:45:00Z", "transmissionSystemDemand": 26932, "nationalDemand": 24600}, {"startTime": "2024-09-10T11:30:00Z", "settlementDate": "2024-09-10", "settlementPeriod": 26, "boundary": "N", "publishTime": "2024-09-10T11:15:00Z", "transmissionSystemDemand": 26711, "nationalDemand": 24257}, {"startTime": "2024-09-10T12:00:00Z", "settlementDate": "2024-09-10", "settlementPeriod": 27, "boundary": "N", "publishTime": "2024-09-10T11:45:00Z", "transmissionSystemDemand": 26949, "nationalDemand": 23787}, {"startTime": "2024-09-10T12:30:00Z", "settlementDate": "2024-09-10", "settlementPeriod": 28, "boundary": "N", "publishTime": "2024-09-10T12:15:00Z", "transmissionSystemDemand": 26812, "nationalDemand": 23530}, {"startTime": "2024-09-10T13:00:00Z", "settlementDate": "2024-09-10", "settlementPeriod": 29, "boundary": "N", "publishTime": "2024-09-10T12:45:00Z", "transmissionSystemDemand": 26134, "nationalDemand": 23019}, {"startTime": "2024-09-10T13:30:00Z", "settlementDate": "2024-09-10", "settlementPeriod": 30, "boundary": "N", "publishTime": "2024-09-10T13:15:00Z", "transmissionSystemDemand": 25978, "nationalDemand": 22900}, {"startTime": "2024-09-10T14:00:00Z", "settlementDate": "2024-09-10", "settlementPeriod": 31, "boundary": "N", "publishTime": "2024-09-10T13:45:00Z", "transmissionSystemDemand": 25591, "nationalDemand": 22980}, {"startTime": "2024-09-10T14:30:00Z", "settlementDate": "2024-09-10", "settlementPeriod": 32, "boundary": "N", "publishTime": "2024-09-10T14:15:00Z", "transmissionSystemDemand": 26379, "nationalDemand": 23770}, {"startTime": "2024-09-10T15:00:00Z", "settlementDate": "2024-09-10", "settlementPeriod": 33, "boundary": "N", "publishTime": "2024-09-10T14:45:00Z", "transmissionSystemDemand": 26996, "nationalDemand": 24919}, {"startTime": "2024-09-10T15:30:00Z", "settlementDate": "2024-09-10", "settlementPeriod": 34, "boundary": "N", "publishTime": "2024-09-10T15:15:00Z", "transmissionSystemDemand": 27193, "nationalDemand": 25699}, {"startTime": "2024-09-10T16:00:00Z", "settlementDate": "2024-09-10", "settlementPeriod": 35, "boundary": "N", "publishTime": "2024-09-10T15:45:00Z", "transmissionSystemDemand": 28165, "nationalDemand": 27002}, {"startTime": "2024-09-10T16:30:00Z", "settlementDate": "2024-09-10", "settlementPeriod": 36, "boundary": "N", "publishTime": "2024-09-10T16:15:00Z", "transmissionSystemDemand": 29016, "nationalDemand": 27895}, {"startTime": "2024-09-10T17:00:00Z", "settlementDate": "2024-09-10", "settlementPeriod": 37, "boundary": "N", "publishTime": "2024-09-10T16:45:00Z", "transmissionSystemDemand": 29557, "nationalDemand": 28412}, {"startTime": "2024-09-10T17:30:00Z", "settlementDate": "2024-09-10", "settlementPeriod": 38, "boundary": "N", "publishTime": "2024-09-10T17:15:00Z", "transmissionSystemDemand": 30007, "nationalDemand": 28900}, {"startTime": "2024-09-10T18:00:00Z", "settlementDate": "2024-09-10", "settlementPeriod": 39, "boundary": "N", "publishTime": "2024-09-10T17:45:00Z", "transmissionSystemDemand": 30611, "nationalDemand": 29330}, {"startTime": "2024-09-10T18:30:00Z", "settlementDate": "2024-09-10", "settlementPeriod": 40, "boundary": "N", "publishTime": "2024-09-10T18:15:00Z", "transmissionSystemDemand": 31168, "nationalDemand": 29800}, {"startTime": "2024-09-10T19:00:00Z", "settlementDate": "2024-09-10", "settlementPeriod": 41, "boundary": "N", "publishTime": "2024-09-10T18:45:00Z", "transmissionSystemDemand": 31149, "nationalDemand": 29640}, {"startTime": "2024-09-10T19:30:00Z", "settlementDate": "2024-09-10", "settlementPeriod": 42, "boundary": "N", "publishTime": "2024-09-10T19:15:00Z", "transmissionSystemDemand": 30122, "nationalDemand": 28572}, {"startTime": "2024-09-10T20:00:00Z", "settlementDate": "2024-09-10", "settlementPeriod": 43, "boundary": "N", "publishTime": "2024-09-10T19:45:00Z", "transmissionSystemDemand": 28796, "nationalDemand": 27198}, {"startTime": "2024-09-10T20:30:00Z", "settlementDate": "2024-09-10", "settlementPeriod": 44, "boundary": "N", "publishTime": "2024-09-10T20:15:00Z", "transmissionSystemDemand": 27414, "nationalDemand": 25816}, {"startTime": "2024-09-10T21:00:00Z", "settlementDate": "2024-09-10", "settlementPeriod": 45, "boundary": "N", "publishTime": "2024-09-10T20:45:00Z", "transmissionSystemDemand": 26322, "nationalDemand": 23874}, {"startTime": "2024-09-10T21:30:00Z", "settlementDate": "2024-09-10", "settlementPeriod": 46, "boundary": "N", "publishTime": "2024-09-10T21:15:00Z", "transmissionSystemDemand": 25164, "nationalDemand": 22575}, {"startTime": "2024-09-10T22:00:00Z", "settlementDate": "2024-09-10", "settlementPeriod": 47, "boundary": "N", "publishTime": "2024-09-10T21:45:00Z", "transmissionSystemDemand": 24856, "nationalDemand": 20830}, {"startTime": "2024-09-10T22:30:00Z", "settlementDate": "2024-09-10", "settlementPeriod": 48, "boundary": "N", "publishTime": "2024-09-10T22:15:00Z", "transmissionSystemDemand": 24114, "nationalDemand": 20000}, {"startTime": "2024-09-10T23:00:00Z", "settlementDate": "2024-09-11", "settlementPeriod": 1, "boundary": "N", "publishTime": "2024-09-10T22:46:00Z", "transmissionSystemDemand": 23565, "nationalDemand": 19000}, {"startTime": "2024-09-10T23:30:00Z", "settlementDate": "2024-09-11", "settlementPeriod": 2, "boundary": "N", "publishTime": "2024-09-10T23:16:00Z", "transmissionSystemDemand": 22884, "nationalDemand": 18416}, {"startTime": "2024-09-11T00:00:00Z", "settlementDate": "2024-09-11", "settlementPeriod": 3, "boundary": "N", "publishTime": "2024-09-10T23:46:00Z", "transmissionSystemDemand": 23242, "nationalDemand": 18100}, {"startTime": "2024-09-11T00:30:00Z", "settlementDate": "2024-09-11", "settlementPeriod": 4, "boundary": "N", "publishTime": "2024-09-11T00:16:00Z", "transmissionSystemDemand": 23170, "nationalDemand": 18100}, {"startTime": "2024-09-11T01:00:00Z", "settlementDate": "2024-09-11", "settlementPeriod": 5, "boundary": "N", "publishTime": "2024-09-11T00:46:00Z", "transmissionSystemDemand": 23136, "nationalDemand": 17963}, {"startTime": "2024-09-11T01:30:00Z", "settlementDate": "2024-09-11", "settlementPeriod": 6, "boundary": "N", "publishTime": "2024-09-11T01:16:00Z", "transmissionSystemDemand": 22703, "nationalDemand": 17506}, {"startTime": "2024-09-11T02:00:00Z", "settlementDate": "2024-09-11", "settlementPeriod": 7, "boundary": "N", "publishTime": "2024-09-11T01:46:00Z", "transmissionSystemDemand": 23264, "nationalDemand": 17443}, {"startTime": "2024-09-11T02:30:00Z", "settlementDate": "2024-09-11", "settlementPeriod": 8, "boundary": "N", "publishTime": "2024-09-11T02:16:00Z", "transmissionSystemDemand": 23016, "nationalDemand": 17294}, {"startTime": "2024-09-11T03:00:00Z", "settlementDate": "2024-09-11", "settlementPeriod": 9, "boundary": "N", "publishTime": "2024-09-11T02:46:00Z", "transmissionSystemDemand": 23020, "nationalDemand": 17200}, {"startTime": "2024-09-11T03:30:00Z", "settlementDate": "2024-09-11", "settlementPeriod": 10, "boundary": "N", "publishTime": "2024-09-11T03:16:00Z", "transmissionSystemDemand": 23186, "nationalDemand": 17372}, {"startTime": "2024-09-11T04:00:00Z", "settlementDate": "2024-09-11", "settlementPeriod": 11, "boundary": "N", "publishTime": "2024-09-11T03:46:00Z", "transmissionSystemDemand": 23545, "nationalDemand": 17848}, {"startTime": "2024-09-11T04:30:00Z", "settlementDate": "2024-09-11", "settlementPeriod": 12, "boundary": "N", "publishTime": "2024-09-11T04:16:00Z", "transmissionSystemDemand": 24363, "nationalDemand": 18723}, {"startTime": "2024-09-11T05:00:00Z", "settlementDate": "2024-09-11", "settlementPeriod": 13, "boundary": "N", "publishTime": "2024-09-11T04:46:00Z", "transmissionSystemDemand": 25024, "nationalDemand": 20818}, {"startTime": "2024-09-11T05:30:00Z", "settlementDate": "2024-09-11", "settlementPeriod": 14, "boundary": "N", "publishTime": "2024-09-11T05:16:00Z", "transmissionSystemDemand": 26014, "nationalDemand": 22422}, {"startTime": "2024-09-11T06:00:00Z", "settlementDate": "2024-09-11", "settlementPeriod": 15, "boundary": "N", "publishTime": "2024-09-11T05:46:00Z", "transmissionSystemDemand": 26214, "nationalDemand": 24702}, {"startTime": "2024-09-11T06:30:00Z", "settlementDate": "2024-09-11", "settlementPeriod": 16, "boundary": "N", "publishTime": "2024-09-11T06:16:00Z", "transmissionSystemDemand": 27166, "nationalDemand": 25600}, {"startTime": "2024-09-11T07:00:00Z", "settlementDate": "2024-09-11", "settlementPeriod": 17, "boundary": "N", "publishTime": "2024-09-11T06:46:00Z", "transmissionSystemDemand": 27537, "nationalDemand": 26100}, {"startTime": "2024-09-11T07:30:00Z", "settlementDate": "2024-09-11", "settlementPeriod": 18, "boundary": "N", "publishTime": "2024-09-11T07:16:00Z", "transmissionSystemDemand": 27078, "nationalDemand": 25593}, {"startTime": "2024-09-11T08:00:00Z", "settlementDate": "2024-09-11", "settlementPeriod": 19, "boundary": "N", "publishTime": "2024-09-11T07:16:00Z", "transmissionSystemDemand": 27158, "nationalDemand": 25184}, {"startTime": "2024-09-11T08:30:00Z", "settlementDate": "2024-09-11", "settlementPeriod": 20, "boundary": "N", "publishTime": "2024-09-11T08:16:00Z", "transmissionSystemDemand": 26698, "nationalDemand": 24468}, {"startTime": "2024-09-11T09:00:00Z", "settlementDate": "2024-09-11", "settlementPeriod": 21, "boundary": "N", "publishTime": "2024-09-11T08:46:00Z", "transmissionSystemDemand": 26150, "nationalDemand": 23766}, {"startTime": "2024-09-11T09:30:00Z", "settlementDate": "2024-09-11", "settlementPeriod": 22, "boundary": "N", "publishTime": "2024-09-11T09:16:00Z", "transmissionSystemDemand": 25833, "nationalDemand": 23368}, {"startTime": "2024-09-11T10:00:00Z", "settlementDate": "2024-09-11", "settlementPeriod": 23, "boundary": "N", "publishTime": "2024-09-11T09:46:00Z", "transmissionSystemDemand": 25837, "nationalDemand": 23029}, {"startTime": "2024-09-11T10:30:00Z", "settlementDate": "2024-09-11", "settlementPeriod": 24, "boundary": "N", "publishTime": "2024-09-11T10:16:00Z", "transmissionSystemDemand": 26060, "nationalDemand": 23486}, {"startTime": "2024-09-11T11:00:00Z", "settlementDate": "2024-09-11", "settlementPeriod": 25, "boundary": "N", "publishTime": "2024-09-11T10:47:00Z", "transmissionSystemDemand": 25260, "nationalDemand": 23200}, {"startTime": "2024-09-11T11:30:00Z", "settlementDate": "2024-09-11", "settlementPeriod": 26, "boundary": "N", "publishTime": "2024-09-11T11:17:00Z", "transmissionSystemDemand": 25064, "nationalDemand": 22994}, {"startTime": "2024-09-11T12:00:00Z", "settlementDate": "2024-09-11", "settlementPeriod": 27, "boundary": "N", "publishTime": "2024-09-11T11:47:00Z", "transmissionSystemDemand": 25212, "nationalDemand": 22599}, {"startTime": "2024-09-11T12:30:00Z", "settlementDate": "2024-09-11", "settlementPeriod": 28, "boundary": "N", "publishTime": "2024-09-11T12:17:00Z", "transmissionSystemDemand": 25029, "nationalDemand": 22511}, {"startTime": "2024-09-11T13:00:00Z", "settlementDate": "2024-09-11", "settlementPeriod": 29, "boundary": "N", "publishTime": "2024-09-11T12:47:00Z", "transmissionSystemDemand": 24651, "nationalDemand": 22300}, {"startTime": "2024-09-11T13:30:00Z", "settlementDate": "2024-09-11", "settlementPeriod": 30, "boundary": "N", "publishTime": "2024-09-11T13:17:00Z", "transmissionSystemDemand": 25088, "nationalDemand": null}, {"startTime": "2024-09-11T14:00:00Z", "settlementDate": "2024-09-11", "settlementPeriod": 31, "boundary": "N", "publishTime": "2024-09-11T13:47:00Z", "transmissionSystemDemand": 25764, "nationalDemand": 23509}, {"startTime": "2024-09-11T14:30:00Z", "settlementDate": "2024-09-11", "settlementPeriod": 32, "boundary": "N", "publishTime": "2024-09-11T14:17:00Z", "transmissionSystemDemand": 25937, "nationalDemand": 24075}, {"startTime": "2024-09-11T15:00:00Z", "settlementDate": "2024-09-11", "settlementPeriod": 33, "boundary": "N", "publishTime": "2024-09-11T14:47:00Z", "transmissionSystemDemand": 28158, "nationalDemand": 25605}, {"startTime": "2024-09-11T15:30:00Z", "settlementDate": "2024-09-11", "settlementPeriod": 34, "boundary": "N", "publishTime": "2024-09-11T15:17:00Z", "transmissionSystemDemand": 28901, "nationalDemand": 26612}, {"startTime": "2024-09-11T16:00:00Z", "settlementDate": "2024-09-11", "settlementPeriod": 35, "boundary": "N", "publishTime": "2024-09-11T15:47:00Z", "transmissionSystemDemand": 30530, "nationalDemand": 27793}, {"startTime": "2024-09-11T16:30:00Z", "settlementDate": "2024-09-11", "settlementPeriod": 36, "boundary": "N", "publishTime": "2024-09-11T16:17:00Z", "transmissionSystemDemand": 31497, "nationalDemand": 28587}, {"startTime": "2024-09-11T17:00:00Z", "settlementDate": "2024-09-11", "settlementPeriod": 37, "boundary": "N", "publishTime": "2024-09-11T16:46:00Z", "transmissionSystemDemand": 31865, "nationalDemand": 29484}, {"startTime": "2024-09-11T17:30:00Z", "settlementDate": "2024-09-11", "settlementPeriod": 38, "boundary": "N", "publishTime": "2024-09-11T17:16:00Z", "transmissionSystemDemand": 32367, "nationalDemand": 30000}, {"startTime": "2024-09-11T18:00:00Z", "settlementDate": "2024-09-11", "settlementPeriod": 39, "boundary": "N", "publishTime": "2024-09-11T17:46:00Z", "transmissionSystemDemand": 31866, "nationalDemand": 30094}, {"startTime": "2024-09-11T18:30:00Z", "settlementDate": "2024-09-11", "settlementPeriod": 40, "boundary": "N", "publishTime": "2024-09-11T18:16:00Z", "transmissionSystemDemand": 32155, "nationalDemand": 30200}, {"startTime": "2024-09-11T19:00:00Z", "settlementDate": "2024-09-11", "settlementPeriod": 41, "boundary": "N", "publishTime": "2024-09-11T18:46:00Z", "transmissionSystemDemand": 31808, "nationalDemand": 29900}, {"startTime": "2024-09-11T19:30:00Z", "settlementDate": "2024-09-11", "settlementPeriod": 42, "boundary": "N", "publishTime": "2024-09-11T19:16:00Z", "transmissionSystemDemand": 30835, "nationalDemand": 28927}, {"startTime": "2024-09-11T20:00:00Z", "settlementDate": "2024-09-11", "settlementPeriod": 43, "boundary": "N", "publishTime": "2024-09-11T19:46:00Z", "transmissionSystemDemand": 30187, "nationalDemand": 27676}, {"startTime": "2024-09-11T20:30:00Z", "settlementDate": "2024-09-11", "settlementPeriod": 44, "boundary": "N", "publishTime": "2024-09-11T20:16:00Z", "transmissionSystemDemand": 29035, "nationalDemand": 26524}, {"startTime": "2024-09-11T21:00:00Z", "settlementDate": "2024-09-11", "settlementPeriod": 45, "boundary": "N", "publishTime": "2024-09-11T20:46:00Z", "transmissionSystemDemand": 26470, "nationalDemand": 24334}, {"startTime": "2024-09-11T21:30:00Z", "settlementDate": "2024-09-11", "settlementPeriod": 46, "boundary": "N", "publishTime": "2024-09-11T21:16:00Z", "transmissionSystemDemand": 24896, "nationalDemand": 23210}, {"startTime": "2024-09-11T22:00:00Z", "settlementDate": "2024-09-11", "settlementPeriod": 47, "boundary": "N", "publishTime": "2024-09-11T21:46:00Z", "transmissionSystemDemand": 24047, "nationalDemand": 21781}, {"startTime": "2024-09-11T22:30:00Z", "settlementDate": "2024-09-11", "settlementPeriod": 48, "boundary": "N", "publishTime": "2024-09-11T22:16:00Z", "transmissionSystemDemand": 23329, "nationalDemand": 21100}, {"startTime": "2024-09-11T23:00:00Z", "settlementDate": "2024-09-12", "settlementPeriod": 1, "boundary": "N", "publishTime": "2024-09-11T22:46:00Z", "transmissionSystemDemand": 23279, "nationalDemand": 20530}, {"startTime": "2024-09-11T23:30:00Z", "settlementDate": "2024-09-12", "settlementPeriod": 2, "boundary": "N", "publishTime": "2024-09-11T23:16:00Z", "transmissionSystemDemand": 22904, "nationalDemand": 20117}, {"startTime": "2024-09-12T00:00:00Z", "settlementDate": "2024-09-12", "settlementPeriod": 3, "boundary": "N", "publishTime": "2024-09-11T23:46:00Z", "transmissionSystemDemand": 22808, "nationalDemand": 19810}, {"startTime": "2024-09-12T00:30:00Z", "settlementDate": "2024-09-12", "settlementPeriod": 4, "boundary": "N", "publishTime": "2024-09-12T00:16:00Z", "transmissionSystemDemand": 22598, "nationalDemand": 19600}, {"startTime": "2024-09-12T01:00:00Z", "settlementDate": "2024-09-12", "settlementPeriod": 5, "boundary": "N", "publishTime": "2024-09-12T00:46:00Z", "transmissionSystemDemand": 22707, "nationalDemand": 19482}, {"startTime": "2024-09-12T01:30:00Z", "settlementDate": "2024-09-12", "settlementPeriod": 6, "boundary": "N", "publishTime": "2024-09-12T01:16:00Z", "transmissionSystemDemand": 22612, "nationalDemand": 19259}, {"startTime": "2024-09-12T02:00:00Z", "settlementDate": "2024-09-12", "settlementPeriod": 7, "boundary": "N", "publishTime": "2024-09-12T01:46:00Z", "transmissionSystemDemand": 22314, "nationalDemand": 18718}, {"startTime": "2024-09-12T02:30:00Z", "settlementDate": "2024-09-12", "settlementPeriod": 8, "boundary": "N", "publishTime": "2024-09-12T02:16:00Z", "transmissionSystemDemand": 22398, "nationalDemand": 18800}, {"startTime": "2024-09-12T03:00:00Z", "settlementDate": "2024-09-12", "settlementPeriod": 9, "boundary": "N", "publishTime": "2024-09-12T02:46:00Z", "transmissionSystemDemand": 22105, "nationalDemand": 18700}, {"startTime": "2024-09-12T03:30:00Z", "settlementDate": "2024-09-12", "settlementPeriod": 10, "boundary": "N", "publishTime": "2024-09-12T03:16:00Z", "transmissionSystemDemand": 22096, "nationalDemand": 18702}, {"startTime": "2024-09-12T04:00:00Z", "settlementDate": "2024-09-12", "settlementPeriod": 11, "boundary": "N", "publishTime": "2024-09-12T03:46:00Z", "transmissionSystemDemand": 23152, "nationalDemand": 19202}, {"startTime": "2024-09-12T04:30:00Z", "settlementDate": "2024-09-12", "settlementPeriod": 12, "boundary": "N", "publishTime": "2024-09-12T04:16:00Z", "transmissionSystemDemand": 23963, "nationalDemand": 20019}, {"startTime": "2024-09-12T05:00:00Z", "settlementDate": "2024-09-12", "settlementPeriod": 13, "boundary": "N", "publishTime": "2024-09-12T04:46:00Z", "transmissionSystemDemand": 26237, "nationalDemand": 22449}, {"startTime": "2024-09-12T05:30:00Z", "settlementDate": "2024-09-12", "settlementPeriod": 14, "boundary": "N", "publishTime": "2024-09-12T05:16:00Z", "transmissionSystemDemand": 28070, "nationalDemand": 24171}, {"startTime": "2024-09-12T06:00:00Z", "settlementDate": "2024-09-12", "settlementPeriod": 15, "boundary": "N", "publishTime": "2024-09-12T05:46:00Z", "transmissionSystemDemand": 28933, "nationalDemand": 26686}, {"startTime": "2024-09-12T06:30:00Z", "settlementDate": "2024-09-12", "settlementPeriod": 16, "boundary": "N", "publishTime": "2024-09-12T06:16:00Z", "transmissionSystemDemand": 29666, "nationalDemand": 27400}, {"startTime": "2024-09-12T07:00:00Z", "settlementDate": "2024-09-12", "settlementPeriod": 17, "boundary": "N", "publishTime": "2024-09-12T06:46:00Z", "transmissionSystemDemand": 29480, "nationalDemand": 28000}, {"startTime": "2024-09-12T07:30:00Z", "settlementDate": "2024-09-12", "settlementPeriod": 18, "boundary": "N", "publishTime": "2024-09-12T07:16:00Z", "transmissionSystemDemand": 28627, "nationalDemand": 27147}, {"startTime": "2024-09-12T08:00:00Z", "settlementDate": "2024-09-12", "settlementPeriod": 19, "boundary": "N", "publishTime": "2024-09-12T07:16:00Z", "transmissionSystemDemand": 28310, "nationalDemand": 26830}, {"startTime": "2024-09-12T08:30:00Z", "settlementDate": "2024-09-12", "settlementPeriod": 20, "boundary": "N", "publishTime": "2024-09-12T08:16:00Z", "transmissionSystemDemand": 27546, "nationalDemand": 26066}, {"startTime": "2024-09-12T09:00:00Z", "settlementDate": "2024-09-12", "settlementPeriod": 21, "boundary": "N", "publishTime": "2024-09-12T08:46:00Z", "transmissionSystemDemand": 26869, "nationalDemand": 25389}, {"startTime": "2024-09-12T09:30:00Z", "settlementDate": "2024-09-12", "settlementPeriod": 22, "boundary": "N", "publishTime": "2024-09-12T09:16:00Z", "transmissionSystemDemand": 26515, "nationalDemand": 25035}, {"startTime": "2024-09-12T10:00:00Z", "settlementDate": "2024-09-12", "settlementPeriod": 23, "boundary": "N", "publishTime": "2024-09-12T09:46:00Z", "transmissionSystemDemand": 26467, "nationalDemand": 24994}, {"startTime": "2024-09-12T10:30:00Z", "settlementDate": "2024-09-12", "settlementPeriod": 24, "boundary": "N", "publishTime": "2024-09-12T10:16:00Z", "transmissionSystemDemand": 27021, "nationalDemand": 25567}, {"startTime": "2024-09-12T11:00:00Z", "settlementDate": "2024-09-12", "settlementPeriod": 25, "boundary": "N", "publishTime": "2024-09-12T10:47:00Z", "transmissionSystemDemand": 27115, "nationalDemand": 25741}, {"startTime": "2024-09-12T11:30:00Z", "settlementDate": "2024-09-12", "settlementPeriod": 26, "boundary": "N", "publishTime": "2024-09-12T11:17:00Z", "transmissionSystemDemand": 27375, "nationalDemand": 26000}, {"startTime": "2024-09-12T12:00:00Z", "settlementDate": "2024-09-12", "settlementPeriod": 27, "boundary": "N", "publishTime": "2024-09-12T11:47:00Z", "transmissionSystemDemand": 26900, "nationalDemand": 25423}, {"startTime": "2024-09-12T12:30:00Z", "settlementDate": "2024-09-12", "settlementPeriod": 28, "boundary": "N", "publishTime": "2024-09-12T12:17:00Z", "transmissionSystemDemand": 26627, "nationalDemand": 25218}, {"startTime": "2024-09-12T13:00:00Z", "settlementDate": "2024-09-12", "settlementPeriod": 29, "boundary": "N", "publishTime": "2024-09-12T12:47:00Z", "transmissionSystemDemand": 26191, "nationalDemand": 24792}, {"startTime": "2024-09-12T13:30:00Z", "settlementDate": "2024-09-12", "settlementPeriod": 30, "boundary": "N", "publishTime": "2024-09-12T13:17:00Z", "transmissionSystemDemand": 25600, "nationalDemand": 24200}, {"startTime": "2024-09-12T14:00:00Z", "settlementDate": "2024-09-12", "settlementPeriod": 31, "boundary": "N", "publishTime": "2024-09-12T13:47:00Z", "transmissionSystemDemand": 26586, "nationalDemand": 24379}, {"startTime": "2024-09-12T14:30:00Z", "settlementDate": "2024-09-12", "settlementPeriod": 32, "boundary": "N", "publishTime": "2024-09-12T14:17:00Z", "transmissionSystemDemand": 27170, "nationalDemand": 24949}, {"startTime": "2024-09-12T15:00:00Z", "settlementDate": "2024-09-12", "settlementPeriod": 33, "boundary": "N", "publishTime": "2024-09-12T14:47:00Z", "transmissionSystemDemand": 28458, "nationalDemand": 25977}, {"startTime": "2024-09-12T15:30:00Z", "settlementDate": "2024-09-12", "settlementPeriod": 34, "boundary": "N", "publishTime": "2024-09-12T15:16:00Z", "transmissionSystemDemand": 30251, "nationalDemand": 27374}, {"startTime": "2024-09-12T16:00:00Z", "settlementDate": "2024-09-12", "settlementPeriod": 35, "boundary": "N", "publishTime": "2024-09-12T15:47:00Z", "transmissionSystemDemand": 32380, "nationalDemand": null}, {"startTime": "2024-09-12T16:30:00Z", "settlementDate": "2024-09-12", "settlementPeriod": 36, "boundary": "N", "publishTime": "2024-09-12T16:16:00Z", "transmissionSystemDemand": 33625, "nationalDemand": 30063}, {"startTime": "2024-09-12T17:00:00Z", "settlementDate": "2024-09-12", "settlementPeriod": 37, "boundary": "N", "publishTime": "2024-09-12T16:47:00Z", "transmissionSystemDemand": 35482, "nationalDemand": 31000}, {"startTime": "2024-09-12T17:30:00Z", "settlementDate": "2024-09-12", "settlementPeriod": 38, "boundary": "N", "publishTime": "2024-09-12T17:16:00Z", "transmissionSystemDemand": 35465, "nationalDemand": 30942}, {"startTime": "2024-09-12T18:00:00Z", "settlementDate": "2024-09-12", "settlementPeriod": 39, "boundary": "N", "publishTime": "2024-09-12T17:46:00Z", "transmissionSystemDemand": 35305, "nationalDemand": 31737}, {"startTime": "2024-09-12T18:30:00Z", "settlementDate": "2024-09-12", "settlementPeriod": 40, "boundary": "N", "publishTime": "2024-09-12T18:16:00Z", "transmissionSystemDemand": 35368, "nationalDemand": 31800}, {"startTime": "2024-09-12T19:00:00Z", "settlementDate": "2024-09-12", "settlementPeriod": 41, "boundary": "N", "publishTime": "2024-09-12T18:47:00Z", "transmissionSystemDemand": 34458, "nationalDemand": 31748}, {"startTime": "2024-09-12T19:30:00Z", "settlementDate": "2024-09-12", "settlementPeriod": 42, "boundary": "N", "publishTime": "2024-09-12T19:17:00Z", "transmissionSystemDemand": 33901, "nationalDemand": 31191}, {"startTime": "2024-09-12T20:00:00Z", "settlementDate": "2024-09-12", "settlementPeriod": 43, "boundary": "N", "publishTime": "2024-09-12T19:46:00Z", "transmissionSystemDemand": 32244, "nationalDemand": 29554}, {"startTime": "2024-09-12T20:30:00Z", "settlementDate": "2024-09-12", "settlementPeriod": 44, "boundary": "N", "publishTime": "2024-09-12T20:16:00Z", "transmissionSystemDemand": 30771, "nationalDemand": 28081}, {"startTime": "2024-09-12T21:00:00Z", "settlementDate": "2024-09-12", "settlementPeriod": 45, "boundary": "N", "publishTime": "2024-09-12T20:46:00Z", "transmissionSystemDemand": 28783, "nationalDemand": 26595}, {"startTime": "2024-09-12T21:30:00Z", "settlementDate": "2024-09-12", "settlementPeriod": 46, "boundary": "N", "publishTime": "2024-09-12T21:16:00Z", "transmissionSystemDemand": 27272, "nationalDemand": 25084}, {"startTime": "2024-09-12T22:00:00Z", "settlementDate": "2024-09-12", "settlementPeriod": 47, "boundary": "N", "publishTime": "2024-09-12T21:46:00Z", "transmissionSystemDemand": 25630, "nationalDemand": 23669}, {"startTime": "2024-09-12T22:30:00Z", "settlementDate": "2024-09-12", "settlementPeriod": 48, "boundary": "N", "publishTime": "2024-09-12T22:16:00Z", "transmissionSystemDemand": 24943, "nationalDemand": 22740}, {"startTime": "2024-09-12T23:00:00Z", "settlementDate": "2024-09-13", "settlementPeriod": 1, "boundary": "N", "publishTime": "2024-09-12T22:46:00Z", "transmissionSystemDemand": 24445, "nationalDemand": 22100}, {"startTime": "2024-09-12T23:30:00Z", "settlementDate": "2024-09-13", "settlementPeriod": 2, "boundary": "N", "publishTime": "2024-09-12T23:16:00Z", "transmissionSystemDemand": 23622, "nationalDemand": 21514}, {"startTime": "2024-09-13T00:00:00Z", "settlementDate": "2024-09-13", "settlementPeriod": 3, "boundary": "N", "publishTime": "2024-09-12T23:46:00Z", "transmissionSystemDemand": 23218, "nationalDemand": 21100}, {"startTime": "2024-09-13T00:30:00Z", "settlementDate": "2024-09-13", "settlementPeriod": 4, "boundary": "N", "publishTime": "2024-09-13T00:15:00Z", "transmissionSystemDemand": 23082, "nationalDemand": 20970}, {"startTime": "2024-09-13T01:00:00Z", "settlementDate": "2024-09-13", "settlementPeriod": 5, "boundary": "N", "publishTime": "2024-09-13T00:45:00Z", "transmissionSystemDemand": 22777, "nationalDemand": 20539}, {"startTime": "2024-09-13T01:30:00Z", "settlementDate": "2024-09-13", "settlementPeriod": 6, "boundary": "N", "publishTime": "2024-09-13T01:15:00Z", "transmissionSystemDemand": 22687, "nationalDemand": 20258}, {"startTime": "2024-09-13T02:00:00Z", "settlementDate": "2024-09-13", "settlementPeriod": 7, "boundary": "N", "publishTime": "2024-09-13T01:45:00Z", "transmissionSystemDemand": 22519, "nationalDemand": 20060}, {"startTime": "2024-09-13T02:30:00Z", "settlementDate": "2024-09-13", "settlementPeriod": 8, "boundary": "N", "publishTime": "2024-09-13T02:15:00Z", "transmissionSystemDemand": 22505, "nationalDemand": 19989}, {"startTime": "2024-09-13T03:00:00Z", "settlementDate": "2024-09-13", "settlementPeriod": 9, "boundary": "N", "publishTime": "2024-09-13T02:45:00Z", "transmissionSystemDemand": 22440, "nationalDemand": 19926}, {"startTime": "2024-09-13T03:30:00Z", "settlementDate": "2024-09-13", "settlementPeriod": 10, "boundary": "N", "publishTime": "2024-09-13T03:15:00Z", "transmissionSystemDemand": 22359, "nationalDemand": 19900}, {"startTime": "2024-09-13T04:00:00Z", "settlementDate": "2024-09-13", "settlementPeriod": 11, "boundary": "N", "publishTime": "2024-09-13T03:45:00Z", "transmissionSystemDemand": 23345, "nationalDemand": 20241}, {"startTime": "2024-09-13T04:30:00Z", "settlementDate": "2024-09-13", "settlementPeriod": 12, "boundary": "N", "publishTime": "2024-09-13T04:15:00Z", "transmissionSystemDemand": 24328, "nationalDemand": 21243}, {"startTime": "2024-09-13T05:00:00Z", "settlementDate": "2024-09-13", "settlementPeriod": 13, "boundary": "N", "publishTime": "2024-09-13T04:45:00Z", "transmissionSystemDemand": 25886, "nationalDemand": 23332}, {"startTime": "2024-09-13T05:30:00Z", "settlementDate": "2024-09-13", "settlementPeriod": 14, "boundary": "N", "publishTime": "2024-09-13T05:15:00Z", "transmissionSystemDemand": 27774, "nationalDemand": 25066}, {"startTime": "2024-09-13T06:00:00Z", "settlementDate": "2024-09-13", "settlementPeriod": 15, "boundary": "N", "publishTime": "2024-09-13T05:45:00Z", "transmissionSystemDemand": 28505, "nationalDemand": 27025}, {"startTime": "2024-09-13T06:30:00Z", "settlementDate": "2024-09-13", "settlementPeriod": 16, "boundary": "N", "publishTime": "2024-09-13T06:15:00Z", "transmissionSystemDemand": 29380, "nationalDemand": 27900}, {"startTime": "2024-09-13T07:00:00Z", "settlementDate": "2024-09-13", "settlementPeriod": 17, "boundary": "N", "publishTime": "2024-09-13T06:45:00Z", "transmissionSystemDemand": 30480, "nationalDemand": 29000}, {"startTime": "2024-09-13T07:30:00Z", "settlementDate": "2024-09-13", "settlementPeriod": 18, "boundary": "N", "publishTime": "2024-09-13T07:15:00Z", "transmissionSystemDemand": 30081, "nationalDemand": 28601}, {"startTime": "2024-09-13T08:00:00Z", "settlementDate": "2024-09-13", "settlementPeriod": 19, "boundary": "N", "publishTime": "2024-09-13T07:15:00Z", "transmissionSystemDemand": 29541, "nationalDemand": 28061}, {"startTime": "2024-09-13T08:30:00Z", "settlementDate": "2024-09-13", "settlementPeriod": 20, "boundary": "N", "publishTime": "2024-09-13T08:15:00Z", "transmissionSystemDemand": 28374, "nationalDemand": 26894}, {"startTime": "2024-09-13T09:00:00Z", "settlementDate": "2024-09-13", "settlementPeriod": 21, "boundary": "N", "publishTime": "2024-09-13T08:45:00Z", "transmissionSystemDemand": 27872, "nationalDemand": 26266}, {"startTime": "2024-09-13T09:30:00Z", "settlementDate": "2024-09-13", "settlementPeriod": 22, "boundary": "N", "publishTime": "2024-09-13T09:15:00Z", "transmissionSystemDemand": 27433, "nationalDemand": 25825}, {"startTime": "2024-09-13T10:00:00Z", "settlementDate": "2024-09-13", "settlementPeriod": 23, "boundary": "N", "publishTime": "2024-09-13T09:45:00Z", "transmissionSystemDemand": 26798, "nationalDemand": 25161}, {"startTime": "2024-09-13T10:30:00Z", "settlementDate": "2024-09-13", "settlementPeriod": 24, "boundary": "N", "publishTime": "2024-09-13T10:15:00Z", "transmissionSystemDemand": 26734, "nationalDemand": 24862}, {"startTime": "2024-09-13T11:00:00Z", "settlementDate": "2024-09-13", "settlementPeriod": 25, "boundary": "N", "publishTime": "2024-09-13T10:45:00Z", "transmissionSystemDemand": 26591, "nationalDemand": 24700}, {"startTime": "2024-09-13T11:30:00Z", "settlementDate": "2024-09-13", "settlementPeriod": 26, "boundary": "N", "publishTime": "2024-09-13T11:15:00Z", "transmissionSystemDemand": 26415, "nationalDemand": 24527}, {"startTime": "2024-09-13T12:00:00Z", "settlementDate": "2024-09-13", "settlementPeriod": 27, "boundary": "N", "publishTime": "2024-09-13T11:45:00Z", "transmissionSystemDemand": 25891, "nationalDemand": 24407}, {"startTime": "2024-09-13T12:30:00Z", "settlementDate": "2024-09-13", "settlementPeriod": 28, "boundary": "N", "publishTime": "2024-09-13T12:15:00Z", "transmissionSystemDemand": 25648, "nationalDemand": 24206}, {"startTime": "2024-09-13T13:00:00Z", "settlementDate": "2024-09-13", "settlementPeriod": 29, "boundary": "N", "publishTime": "2024-09-13T12:45:00Z", "transmissionSystemDemand": 25561, "nationalDemand": 24081}, {"startTime": "2024-09-13T13:30:00Z", "settlementDate": "2024-09-13", "settlementPeriod": 30, "boundary": "N", "publishTime": "2024-09-13T13:15:00Z", "transmissionSystemDemand": 25412, "nationalDemand": 24000}, {"startTime": "2024-09-13T14:00:00Z", "settlementDate": "2024-09-13", "settlementPeriod": 31, "boundary": "N", "publishTime": "2024-09-13T13:45:00Z", "transmissionSystemDemand": 25289, "nationalDemand": 24004}, {"startTime": "2024-09-13T14:30:00Z", "settlementDate": "2024-09-13", "settlementPeriod": 32, "boundary": "N", "publishTime": "2024-09-13T14:15:00Z", "transmissionSystemDemand": 25765, "nationalDemand": 24501}, {"startTime": "2024-09-13T15:00:00Z", "settlementDate": "2024-09-13", "settlementPeriod": 33, "boundary": "N", "publishTime": "2024-09-13T14:45:00Z", "transmissionSystemDemand": 26720, "nationalDemand": 25538}, {"startTime": "2024-09-13T15:30:00Z", "settlementDate": "2024-09-13", "settlementPeriod": 34, "boundary": "N", "publishTime": "2024-09-13T15:15:00Z", "transmissionSystemDemand": 28027, "nationalDemand": 26821}, {"startTime": "2024-09-13T16:00:00Z", "settlementDate": "2024-09-13", "settlementPeriod": 35, "boundary": "N", "publishTime": "2024-09-13T15:45:00Z", "transmissionSystemDemand": 29229, "nationalDemand": 28027}, {"startTime": "2024-09-13T16:30:00Z", "settlementDate": "2024-09-13", "settlementPeriod": 36, "boundary": "N", "publishTime": "2024-09-13T16:15:00Z", "transmissionSystemDemand": 29891, "nationalDemand": 28949}, {"startTime": "2024-09-13T17:00:00Z", "settlementDate": "2024-09-13", "settlementPeriod": 37, "boundary": "N", "publishTime": "2024-09-13T16:45:00Z", "transmissionSystemDemand": 30367, "nationalDemand": 29542}, {"startTime": "2024-09-13T17:30:00Z", "settlementDate": "2024-09-13", "settlementPeriod": 38, "boundary": "N", "publishTime": "2024-09-13T17:15:00Z", "transmissionSystemDemand": 30965, "nationalDemand": 30200}, {"startTime": "2024-09-13T18:00:00Z", "settlementDate": "2024-09-13", "settlementPeriod": 39, "boundary": "N", "publishTime": "2024-09-13T17:45:00Z", "transmissionSystemDemand": 31478, "nationalDemand": 30731}, {"startTime": "2024-09-13T18:30:00Z", "settlementDate": "2024-09-13", "settlementPeriod": 40, "boundary": "N", "publishTime": "2024-09-13T18:15:00Z", "transmissionSystemDemand": 31610, "nationalDemand": 30900}, {"startTime": "2024-09-13T19:00:00Z", "settlementDate": "2024-09-13", "settlementPeriod": 41, "boundary": "N", "publishTime": "2024-09-13T18:45:00Z", "transmissionSystemDemand": 31127, "nationalDemand": 30558}, {"startTime": "2024-09-13T19:30:00Z", "settlementDate": "2024-09-13", "settlementPeriod": 42, "boundary": "N", "publishTime": "2024-09-13T19:15:00Z", "transmissionSystemDemand": 30186, "nationalDemand": 29558}, {"startTime": "2024-09-13T20:00:00Z", "settlementDate": "2024-09-13", "settlementPeriod": 43, "boundary": "N", "publishTime": "2024-09-13T19:45:00Z", "transmissionSystemDemand": 28830, "nationalDemand": 28141}, {"startTime": "2024-09-13T20:30:00Z", "settlementDate": "2024-09-13", "settlementPeriod": 44, "boundary": "N", "publishTime": "2024-09-13T20:15:00Z", "transmissionSystemDemand": 27649, "nationalDemand": 26853}, {"startTime": "2024-09-13T21:00:00Z", "settlementDate": "2024-09-13", "settlementPeriod": 45, "boundary": "N", "publishTime": "2024-09-13T20:45:00Z", "transmissionSystemDemand": 26142, "nationalDemand": 25423}, {"startTime": "2024-09-13T21:30:00Z", "settlementDate": "2024-09-13", "settlementPeriod": 46, "boundary": "N", "publishTime": "2024-09-13T21:15:00Z", "transmissionSystemDemand": 24963, "nationalDemand": 24144}, {"startTime": "2024-09-13T22:00:00Z", "settlementDate": "2024-09-13", "settlementPeriod": 47, "boundary": "N", "publishTime": "2024-09-13T21:45:00Z", "transmissionSystemDemand": 23774, "nationalDemand": 22626}, {"startTime": "2024-09-13T22:30:00Z", "settlementDate": "2024-09-13", "settlementPeriod": 48, "boundary": "N", "publishTime": "2024-09-13T22:15:00Z", "transmissionSystemDemand": 22917, "nationalDemand": 21800}, {"startTime": "2024-09-13T23:00:00Z", "settlementDate": "2024-09-14", "settlementPeriod": 1, "boundary": "N", "publishTime": "2024-09-13T22:45:00Z", "transmissionSystemDemand": 21362, "nationalDemand": 20730}, {"startTime": "2024-09-13T23:30:00Z", "settlementDate": "2024-09-14", "settlementPeriod": 2, "boundary": "N", "publishTime": "2024-09-13T23:15:00Z", "transmissionSystemDemand": 20664, "nationalDemand": 20095}, {"startTime": "2024-09-14T00:00:00Z", "settlementDate": "2024-09-14", "settlementPeriod": 3, "boundary": "N", "publishTime": "2024-09-13T23:45:00Z", "transmissionSystemDemand": 20159, "nationalDemand": 19490}, {"startTime": "2024-09-14T00:30:00Z", "settlementDate": "2024-09-14", "settlementPeriod": 4, "boundary": "N", "publishTime": "2024-09-14T00:15:00Z", "transmissionSystemDemand": 20296, "nationalDemand": 19400}, {"startTime": "2024-09-14T01:00:00Z", "settlementDate": "2024-09-14", "settlementPeriod": 5, "boundary": "N", "publishTime": "2024-09-14T00:45:00Z", "transmissionSystemDemand": 20546, "nationalDemand": 19109}, {"startTime": "2024-09-14T01:30:00Z", "settlementDate": "2024-09-14", "settlementPeriod": 6, "boundary": "N", "publishTime": "2024-09-14T01:15:00Z", "transmissionSystemDemand": 20021, "nationalDemand": 18558}, {"startTime": "2024-09-14T02:00:00Z", "settlementDate": "2024-09-14", "settlementPeriod": 7, "boundary": "N", "publishTime": "2024-09-14T01:45:00Z", "transmissionSystemDemand": 19859, "nationalDemand": 18145}, {"startTime": "2024-09-14T02:30:00Z", "settlementDate": "2024-09-14", "settlementPeriod": 8, "boundary": "N", "publishTime": "2024-09-14T02:15:00Z", "transmissionSystemDemand": 19542, "nationalDemand": 17887}, {"startTime": "2024-09-14T03:00:00Z", "settlementDate": "2024-09-14", "settlementPeriod": 9, "boundary": "N", "publishTime": "2024-09-14T02:45:00Z", "transmissionSystemDemand": 19542, "nationalDemand": 17779}, {"startTime": "2024-09-14T03:30:00Z", "settlementDate": "2024-09-14", "settlementPeriod": 10, "boundary": "N", "publishTime": "2024-09-14T03:15:00Z", "transmissionSystemDemand": 19462, "nationalDemand": 17700}, {"startTime": "2024-09-14T04:00:00Z", "settlementDate": "2024-09-14", "settlementPeriod": 11, "boundary": "N", "publishTime": "2024-09-14T03:45:00Z", "transmissionSystemDemand": 19987, "nationalDemand": 18073}, {"startTime": "2024-09-14T04:30:00Z", "settlementDate": "2024-09-14", "settlementPeriod": 12, "boundary": "N", "publishTime": "2024-09-14T04:15:00Z", "transmissionSystemDemand": 20243, "nationalDemand": 18416}, {"startTime": "2024-09-14T05:00:00Z", "settlementDate": "2024-09-14", "settlementPeriod": 13, "boundary": "N", "publishTime": "2024-09-14T04:45:00Z", "transmissionSystemDemand": 21005, "nationalDemand": 19469}, {"startTime": "2024-09-14T05:30:00Z", "settlementDate": "2024-09-14", "settlementPeriod": 14, "boundary": "N", "publishTime": "2024-09-14T05:15:00Z", "transmissionSystemDemand": 21553, "nationalDemand": 20022}, {"startTime": "2024-09-14T06:00:00Z", "settlementDate": "2024-09-14", "settlementPeriod": 15, "boundary": "N", "publishTime": "2024-09-14T05:45:00Z", "transmissionSystemDemand": 22598, "nationalDemand": 21201}, {"startTime": "2024-09-14T06:30:00Z", "settlementDate": "2024-09-14", "settlementPeriod": 16, "boundary": "N", "publishTime": "2024-09-14T06:15:00Z", "transmissionSystemDemand": 23397, "nationalDemand": 22000}, {"startTime": "2024-09-14T07:00:00Z", "settlementDate": "2024-09-14", "settlementPeriod": 17, "boundary": "N", "publishTime": "2024-09-14T06:45:00Z", "transmissionSystemDemand": 23734, "nationalDemand": 22500}, {"startTime": "2024-09-14T07:30:00Z", "settlementDate": "2024-09-14", "settlementPeriod": 18, "boundary": "N", "publishTime": "2024-09-14T07:16:00Z", "transmissionSystemDemand": 23602, "nationalDemand": 22368}, {"startTime": "2024-09-14T08:00:00Z", "settlementDate": "2024-09-14", "settlementPeriod": 19, "boundary": "N", "publishTime": "2024-09-14T07:16:00Z", "transmissionSystemDemand": 23216, "nationalDemand": 22209}, {"startTime": "2024-09-14T08:30:00Z", "settlementDate": "2024-09-14", "settlementPeriod": 20, "boundary": "N", "publishTime": "2024-09-14T08:16:00Z", "transmissionSystemDemand": 23324, "nationalDemand": 21736}, {"startTime": "2024-09-14T09:00:00Z", "settlementDate": "2024-09-14", "settlementPeriod": 21, "boundary": "N", "publishTime": "2024-09-14T08:46:00Z", "transmissionSystemDemand": 22998, "nationalDemand": 21042}, {"startTime": "2024-09-14T09:30:00Z", "settlementDate": "2024-09-14", "settlementPeriod": 22, "boundary": "N", "publishTime": "2024-09-14T09:16:00Z", "transmissionSystemDemand": 22556, "nationalDemand": 20393}, {"startTime": "2024-09-14T10:00:00Z", "settlementDate": "2024-09-14", "settlementPeriod": 23, "boundary": "N", "publishTime": "2024-09-14T09:46:00Z", "transmissionSystemDemand": 22519, "nationalDemand": 19848}, {"startTime": "2024-09-14T10:30:00Z", "settlementDate": "2024-09-14", "settlementPeriod": 24, "boundary": "N", "publishTime": "2024-09-14T10:16:00Z", "transmissionSystemDemand": 22314, "nationalDemand": 19558}, {"startTime": "2024-09-14T11:00:00Z", "settlementDate": "2024-09-14", "settlementPeriod": 25, "boundary": "N", "publishTime": "2024-09-14T10:47:00Z", "transmissionSystemDemand": 22754, "nationalDemand": 19500}, {"startTime": "2024-09-14T11:30:00Z", "settlementDate": "2024-09-14", "settlementPeriod": 26, "boundary": "N", "publishTime": "2024-09-14T11:17:00Z", "transmissionSystemDemand": 22699, "nationalDemand": 19369}, {"startTime": "2024-09-14T12:00:00Z", "settlementDate": "2024-09-14", "settlementPeriod": 27, "boundary": "N", "publishTime": "2024-09-14T11:45:00Z", "transmissionSystemDemand": 22700, "nationalDemand": 19184}, {"startTime": "2024-09-14T12:30:00Z", "settlementDate": "2024-09-14", "settlementPeriod": 28, "boundary": "N", "publishTime": "2024-09-14T12:15:00Z", "transmissionSystemDemand": 22260, "nationalDemand": 18730}, {"startTime": "2024-09-14T13:00:00Z", "settlementDate": "2024-09-14", "settlementPeriod": 29, "boundary": "N", "publishTime": "2024-09-14T12:45:00Z", "transmissionSystemDemand": 22063, "nationalDemand": 18500}, {"startTime": "2024-09-14T13:30:00Z", "settlementDate": "2024-09-14", "settlementPeriod": 30, "boundary": "N", "publishTime": "2024-09-14T13:15:00Z", "transmissionSystemDemand": 22213, "nationalDemand": 18628}, {"startTime": "2024-09-14T14:00:00Z", "settlementDate": "2024-09-14", "settlementPeriod": 31, "boundary": "N", "publishTime": "2024-09-14T13:45:00Z", "transmissionSystemDemand": 22445, "nationalDemand": 18725}, {"startTime": "2024-09-14T14:30:00Z", "settlementDate": "2024-09-14", "settlementPeriod": 32, "boundary": "N", "publishTime": "2024-09-14T14:15:00Z", "transmissionSystemDemand": 22924, "nationalDemand": 19278}, {"startTime": "2024-09-14T15:00:00Z", "settlementDate": "2024-09-14", "settlementPeriod": 33, "boundary": "N", "publishTime": "2024-09-14T14:45:00Z", "transmissionSystemDemand": 23565, "nationalDemand": 20176}, {"startTime": "2024-09-14T15:30:00Z", "settlementDate": "2024-09-14", "settlementPeriod": 34, "boundary": "N", "publishTime": "2024-09-14T15:16:00Z", "transmissionSystemDemand": 24255, "nationalDemand": 21519}, {"startTime": "2024-09-14T16:00:00Z", "settlementDate": "2024-09-14", "settlementPeriod": 35, "boundary": "N", "publishTime": "2024-09-14T15:45:00Z", "transmissionSystemDemand": 25704, "nationalDemand": 23166}, {"startTime": "2024-09-14T16:30:00Z", "settlementDate": "2024-09-14", "settlementPeriod": 36, "boundary": "N", "publishTime": "2024-09-14T16:15:00Z", "transmissionSystemDemand": 26847, "nationalDemand": 24478}, {"startTime": "2024-09-14T17:00:00Z", "settlementDate": "2024-09-14", "settlementPeriod": 37, "boundary": "N", "publishTime": "2024-09-14T16:45:00Z", "transmissionSystemDemand": 26457, "nationalDemand": 25020}, {"startTime": "2024-09-14T17:30:00Z", "settlementDate": "2024-09-14", "settlementPeriod": 38, "boundary": "N", "publishTime": "2024-09-14T17:15:00Z", "transmissionSystemDemand": 27012, "nationalDemand": 25530}, {"startTime": "2024-09-14T18:00:00Z", "settlementDate": "2024-09-14", "settlementPeriod": 39, "boundary": "N", "publishTime": "2024-09-14T17:45:00Z", "transmissionSystemDemand": 27427, "nationalDemand": 25949}, {"startTime": "2024-09-14T18:30:00Z", "settlementDate": "2024-09-14", "settlementPeriod": 40, "boundary": "N", "publishTime": "2024-09-14T18:15:00Z", "transmissionSystemDemand": 28178, "nationalDemand": 26600}, {"startTime": "2024-09-14T19:00:00Z", "settlementDate": "2024-09-14", "settlementPeriod": 41, "boundary": "N", "publishTime": "2024-09-14T18:45:00Z", "transmissionSystemDemand": 27630, "nationalDemand": 25982}, {"startTime": "2024-09-14T19:30:00Z", "settlementDate": "2024-09-14", "settlementPeriod": 42, "boundary": "N", "publishTime": "2024-09-14T19:15:00Z", "transmissionSystemDemand": 26949, "nationalDemand": 25193}, {"startTime": "2024-09-14T20:00:00Z", "settlementDate": "2024-09-14", "settlementPeriod": 43, "boundary": "N", "publishTime": "2024-09-14T19:45:00Z", "transmissionSystemDemand": 26378, "nationalDemand": 24414}, {"startTime": "2024-09-14T20:30:00Z", "settlementDate": "2024-09-14", "settlementPeriod": 44, "boundary": "N", "publishTime": "2024-09-14T20:15:00Z", "transmissionSystemDemand": 25493, "nationalDemand": 23529}, {"startTime": "2024-09-14T21:00:00Z", "settlementDate": "2024-09-14", "settlementPeriod": 45, "boundary": "N", "publishTime": "2024-09-14T20:45:00Z", "transmissionSystemDemand": 24846, "nationalDemand": 22473}, {"startTime": "2024-09-14T21:30:00Z", "settlementDate": "2024-09-14", "settlementPeriod": 46, "boundary": "N", "publishTime": "2024-09-14T21:15:00Z", "transmissionSystemDemand": 23132, "nationalDemand": 21209}, {"startTime": "2024-09-14T22:00:00Z", "settlementDate": "2024-09-14", "settlementPeriod": 47, "boundary": "N", "publishTime": "2024-09-14T21:45:00Z", "transmissionSystemDemand": 23754, "nationalDemand": 20433}, {"startTime": "2024-09-14T22:30:00Z", "settlementDate": "2024-09-14", "settlementPeriod": 48, "boundary": "N", "publishTime": "2024-09-14T22:16:00Z", "transmissionSystemDemand": 23291, "nationalDemand": 19510}, {"startTime": "2024-09-14T23:00:00Z", "settlementDate": "2024-09-15", "settlementPeriod": 1, "boundary": "N", "publishTime": "2024-09-14T22:46:00Z", "transmissionSystemDemand": 22322, "nationalDemand": 18790}, {"startTime": "2024-09-14T23:30:00Z", "settlementDate": "2024-09-15", "settlementPeriod": 2, "boundary": "N", "publishTime": "2024-09-14T23:16:00Z", "transmissionSystemDemand": 21941, "nationalDemand": 18411}, {"startTime": "2024-09-15T00:00:00Z", "settlementDate": "2024-09-15", "settlementPeriod": 3, "boundary": "N", "publishTime": "2024-09-14T23:46:00Z", "transmissionSystemDemand": 21322, "nationalDemand": 18010}]}